Workbook

Sheet Summery
A1: Daily | E1: Weeks | I1: Month | M1: Cheque
A2: Loan Amount | B2: Received | C2: Interest | D2: To be Received | E2: Loan Amount | F2: Received | G2: Interest | H2: To be Received | I2: Loan Amount | J2: Received | K2: Interest | L2: To be Received | M2: Loan | N2: Total Cash Received | O2: Interest | P2: To be Rec
A3: =SUM(Daily!G:G) -> 210000 | B3: =SUM(Daily!K:K) -> 252000 | C3: =SUMIF(Daily!L2:L13,">0") -> 42000 | D3: =SUM(Daily!M:M) -> -42000 | E3: =SUM(Weekly!H:H) -> 45000 | F3: =SUM(Weekly!L:L) -> 54000 | G3: =SUMIF(Weekly!M2:M7,">0") -> 9000 | H3: =SUM(Weekly!N:N) -> -9000 | I3: =SUM(#REF!) -> #REF! | J3: =SUM(#REF!) -> #REF! | K3: =SUMIF(#REF!,">0") -> #REF! | L3: =SUM(#REF!) -> #REF! | M3: =SUM(#REF!) -> #REF! | N3: =SUM(#REF!) -> #REF! | O3: =SUM(#REF!) -> #REF! | P3: =M3-N3 -> #REF!
A5: Loan Amount | B5: =A3+E3+I3+M3 -> #REF! | D5: Capitals
A6: Received | B6: =B3+F3+J3+N3 -> #REF! | D6: S | F6: C | H6: R | J6: CSR
A7: Interest | B7: =C3+G3+K3+O3 -> #REF! | D7: In | E7: Out | F7: In | G7: Out | H7: In | I7: Out
A8: To be Received | B8: =D3+H3+L3+P3 -> #REF! | D8: =SUM('Capital Edited'!C:C) -> 542000 | E8: =SUM('Capital Edited'!D:D) -> 52000 | F8: =SUM('Capital Edited'!E:E) -> 40000 | G8: =SUM('Capital Edited'!F:F) -> 0 | H8: =SUM('Capital Edited'!G:G) -> 0 | I8: =SUM('Capital Edited'!H:H) -> 0
D9: =D8-E8 -> 490000 | F9: =F8-G8 -> 40000 | H9: =H8-I8 -> 0
D10: =D9+F9+H9 -> 530000
A11: To be received | B11: =B8 -> #REF!
A12: Other Expenses | B12: =SUM('Expences & Other Income'!O:O) -> 17720 | J12: =D10 -> 530000 | K12: 800000 | L12: tire
A13: Profit dividens | B13: =SUM(Profits!F:F) -> 62000 | I13: fish | J13: -600000 | K13: =D10+K12 -> 1330000
A14: Cash in hand | B14: 10550 | I14: tire | J14: =-(400000+85000+15000) -> -500000 | K14: =100000+28000 -> 128000
A15: Cash in Boc | B15: 0 | D15: Total Incom | E15: =B7 -> #REF! | F15: =C3+G3 -> 51000 | I15: lahiru | J15: =50000-50000 -> 0 | K15: =SUM(K13:K14) -> 1458000
A16: Other | B16: 0 | D16: Other Expenses | E16: =B12 -> 17720 | F16: =E16 -> 17720 | I16: fish income | J16: =SUM(#REF!) -> #REF!
A17: Portfoliyo | B17: =SUM(B11:B16) -> #REF! | D17: Profit | E17: =E15-E16 -> #REF! | F17: =F15-F16 -> 33280 | J17: =SUM(J12:J16) -> #REF!
D18: Dividens | E18: =B13 -> 62000 | J18: =B7 -> #REF!
D19: Rest Profit | E19: =E17-E18 -> #REF! | J19: =J17+J18 -> #REF!
A20: Total Investment | B20: =J19 -> #REF!
A21: Portfilio | B21: =B17 -> #REF! | J21: 1800000
A22: Difference | B22: =B20-B21 -> #REF! | J22: =J19+J21 -> #REF!
B23: 262000

Sheet Month
A1: Date | B1: 1 | C1: Date | D1: 2 | E1: Date | F1: 3 | G1: Date | H1: 4 | I1: Date | J1: 5 | K1: Date | L1: 6 | N1: 7 | P1: 8 | R1: 9 | T1: 10 | V1: 11 | X1: 12 | Z1: 13 | AB1: 14 | AD1: 15 | AF1: 16 | AH1: 17 | AJ1: 18 | AL1: 19 | AN1: 20 | AP1: 21 | AR1: 22 | AT1: 23 | AV1: 24 | AX1: 25 | AY1: 26 | BA1: 27 | BC1: 28 | BE1: 29 | BG1: 30 | BH1: 31 | BI1: 32 | BJ1: 33 | BK1: 34 | BL1: 35 | BM1: 36 | BN1: 37 | BO1: 38 | BP1: 39 | BQ1: 40 | BR1: 41 | BS1: 42 | BT1: 43 | BU1: 44 | BV1: 45 | BW1: 46 | BX1: 47 | BY1: 48 | BZ1: 49 | CA1: 50 | CB1: 51 | CC1: 52 | CD1: 53 | CE1: 54 | CF1: 55 | CG1: 56 | CH1: 57 | CI1: 58 | CJ1: 59 | CK1: 60 | CL1: 61 | CM1: 62 | CN1: 63 | CO1: 64 | CP1: 65 | CQ1: 66 | CR1: 67 | CS1: 68 | CT1: 69 | CU1: 70 | CV1: 71
B2: Manju | D2: HG Saman | F2: Sena | H2: Samapath | J2: Renuka | L2: Hema | N2: WB Dilshan | P2: Janaka | R2: Bandura | T2: KG Anil | V2: RW Wimaladasa | X2: Bashitha | Z2: MG Nimali | AB2: Lakshan | AD2: chamila | AF2: Vijemali | AH2: Bimsara | AJ2: Hashan | AL2: Samantha | AN2: Wasanthi | AP2: Jayathissa(Ekanayaka | AR2: Hiran | AT2: Muditha | AV2: Bimsara | AX2: Rajakaruna | AY2: Terry | BA2: SK Inoka lakmal | BC2: Jayantha | BE2: Podi | BG2: Ramanadan
B4: 0.1 | D4: 0.1 | F4: 0.1 | H4: 0.1 | J4: 0.1 | L4: 0.1 | N4: 0.1 | P4: 0.1 | R4: 0.1 | T4: 0.1 | V4: 0.1 | X4: 0.1 | Z4: 0.1 | AB4: 0.1 | AD4: 0.1 | AF4: 0.1 | AH4: 0.1 | AJ4: 0.1 | AL4: 0.1 | AN4: 0.1 | AP4: 0.1 | AR4: 0.1 | AT4: 0.1 | AV4: 0.1 | AX4: 0.1 | AY4: 0.1 | BA4: 0.1 | BC4: 0.1 | BE4: 0.1 | BG4: 0.1 | BH4: 0.1 | BI4: 0.1 | BJ4: 0.1 | BK4: 0.1 | BL4: 0.1 | BM4: 0.1 | BN4: 0.1 | BO4: 0.1 | BP4: 0.1 | BQ4: 0.1 | BR4: 0.1 | BS4: 0.1 | BT4: 0.1 | BU4: 0.1 | BV4: 0.1 | BW4: 0.1 | BX4: 0.1 | BY4: 0.1 | BZ4: 0.1 | CA4: 0.1 | CB4: 0.1 | CC4: 0.1 | CD4: 0.1 | CE4: 0.1 | CF4: 0.1 | CG4: 0.1 | CH4: 0.1 | CI4: 0.1 | CJ4: 0.1 | CK4: 0.1 | CL4: 0.1 | CM4: 0.1 | CN4: 0.1
B5: 50000 | D5: 10000 | F5: 5000 | H5: =50000-30000 -> 20000 | J5: =10000-2000 -> 8000 | L5: 20000 | N5: 15000 | P5: 25000 | R5: 80000 | T5: 30000 | V5: 20000 | X5: 350000 | Z5: 50000 | AB5: 170000 | AD5: 500000 | AF5: 25000 | AH5: 20000 | AJ5: 100000 | AL5: 300000 | AN5: 10000 | AP5: 100000 | AR5: 200000 | AT5: 50000 | AV5: 50000 | AX5: 30000 | AY5: 215000 | BA5: 15000 | BC5: 200000 | BE5: 65000 | BG5: 5000
D6: 1000 | F6: 0 | H6: =4000+4000 -> 8000 | J6: 1000
D7: 1000

Sheet Daily
A1: D001 | B1: Name | D1: T.P | E1: Isuue date | F1: Due date | G1: Loan Amount | H1: Interest Rate | I1: Installment Amount | J1: No of installment | K1: Received | L1: Interest | M1: To be Received | N1: Total Payments
A2: D001 | B2: KBTD Chamani | D2: 779907450 | E2: 45856 | F2: =E2+60 -> 45916 | G2: 25000 | H2: 0.1 | I2: 500 | J2: 60 | K2: =I2*J2 -> 30000 | L2: =K2-G2 -> 5000 | M2: =G2-K2 -> -5000 | N2: =G2*(1+H2*2) -> 30000 | O2: =E2+1 -> 45857 | P2: =O2+1 -> 45858 | Q2: =P2+1 -> 45859 | R2: =Q2+1 -> 45860 | S2: =R2+1 -> 45861 | T2: =S2+1 -> 45862 | U2: =T2+1 -> 45863 | V2: =U2+1 -> 45864 | W2: =V2+1 -> 45865 | ... AY2: =AX2+1 -> 45893
K3: =I3*J3 -> 0 | L3: =K3-G3 -> 0 | M3: =G3-K3 -> 0 | O3: 500 | P3: 500 | Q3: 500 | R3: 500 | S3: 500 | T3: 500 | U3: 500 | V3: 500 | W3: 500 | X3: 500 | Y3: 500 | Z3: 500 | AA3: 500 | AB3: 500 | AC3: 500 | AD3: 500 | AE3: 500 | AF3: 500 | AG3: 500 | AH3: 500 | AI3: 500 | AJ3: 500 | AK3: 500 | AL3: 500 | AM3: 500 | AN3: 500 | AO3: 500 | AP3: 500 | AQ3: 500 | AR3: 500 | AS3: 500 | AT3: 500 | AU3: 500 | AV3: 500 | AW3: 500 | AX3: 500 | AY3: 500
A4: D002 | B4: KA Prasanna | D4: 776088166 | E4: 45857 | F4: =E4+60 -> 45917 | G4: 50000 | H4: 0.1 | I4: 1000 | J4: =N4/I4 -> 60 | K4: =I4*J4 -> 60000 | L4: =K4-G4 -> 10000 | M4: =G4-K4 -> -10000 | N4: =G4*(1+H4*2) -> 60000
K5: =I5*J5 -> 0 | L5: =K5-G5 -> 0 | M5: =G5-K5 -> 0
A6: 3 | B6: HA Nanadasena | D6: 768675303 | E6: 45859 | F6: =E6+60 -> 45919 | G6: 60000 | H6: 0.1 | I6: 1200 | J6: =N6/I6 -> 60 | K6: =I6*J6 -> 72000 | L6: =K6-G6 -> 12000 | M6: =G6-K6 -> -12000 | N6: =G6*(1+H6*2) -> 72000
K7: =I7*J7 -> 0 | L7: =K7-G7 -> 0 | M7: =G7-K7 -> 0
A8: 4 | B8: P Manesh | D8: 779142768 | E8: 45859 | F8: =E8+60 -> 45919 | G8: 20000 | H8: 0.1 | I8: 400 | J8: =N8/I8 -> 60 | K8: =I8*J8 -> 24000 | L8: =K8-G8 -> 4000 | M8: =G8-K8 -> -4000 | N8: =G8*(1+H8*2) -> 24000
K9: =I9*J9 -> 0 | L9: =K9-G9 -> 0 | M9: =G9-K9 -> 0
A10: 5 | B10: MGN Kumara | D10: 770518864 | E10: 45859 | F10: =E10+60 -> 45919 | G10: 25000 | H10: 0.1 | I10: 500 | J10: =N10/I10 -> 60 | K10: =I10*J10 -> 30000 | L10: =K10-G10 -> 5000 | M10: =G10-K10 -> -5000 | N10: =G10*(1+H10*2) -> 30000
K11: =I11*J11 -> 0 | L11: =K11-G11 -> 0 | M11: =G11-K11 -> 0
A12: 6 | B12: GG Buddhika | D12: 772196918 | E12: 45860 | F12: =E12+60 -> 45920 | G12: 30000 | H12: 0.1 | I12: 600 | J12: =N12/I12 -> 60 | K12: =I12*J12 -> 36000 | L12: =K12-G12 -> 6000 | M12: =G12-K12 -> -6000 | N12: =G12*(1+H12*2) -> 36000
K13: =I13*J13 -> 0 | L13: =K13-G13 -> 0 | M13: =G13-K13 -> 0

Sheet Weekly
A1: Wno | B1: Name | C1: Location | E1: T.P | F1: Isuue date | G1: Due date | H1: Loan Amount | I1: Interest Rate | J1: Installment Amount | K1: No of installment | L1: Received sofar | M1: Interest | N1: To be Received | O1: Total Payments
A2: 1 | B2: BH Surangani | C2: Thalagaswela | E2: 767850049 | F2: 45856 | G2: =F2+60 -> 45916 | H2: 20000 | I2: 0.1 | J2: =(H2+H2*0.2)/8 -> 3000 | K2: 8 | L2: =J2*K2 -> 24000 | M2: =L2-H2 -> 4000 | N2: =H2-L2 -> -4000 | O2: =H2*(1+I2*2) -> 24000
J3: =(H3+H3*0.2)/8 -> 0 | L3: =J3*K3 -> 0 | M3: =L3-H3 -> 0 | N3: =H3-L3 -> 0
A4: 2 | B4: BH Shriyani | C4: Thalagaswela | E4: 783891636 | F4: 45856 | H4: 20000 | I4: 0.1 | J4: =(H4+H4*0.2)/8 -> 3000 | K4: 8 | L4: =J4*K4 -> 24000 | M4: =L4-H4 -> 4000 | N4: =H4-L4 -> -4000 | O4: =H4*(1+I4*2) -> 24000
J5: =(H5+H5*0.2)/8 -> 0 | L5: =J5*K5 -> 0 | M5: =L5-H5 -> 0 | N5: =H5-L5 -> 0
A6: 3 | B6: LA Damayanthi | C6: Watte | E6: 762396051 | F6: 45859 | H6: 5000 | J6: =(H6+H6*0.2)/8 -> 750 | K6: 8 | L6: =J6*K6 -> 6000 | M6: =L6-H6 -> 1000 | N6: =H6-L6 -> -1000
J7: =(H7+H7*0.2)/8 -> 0 | L7: =J7*K7 -> 0 | M7: =L7-H7 -> 0 | N7: =H7-L7 -> 0
J8: =(H8+H8*0.2)/8 -> 0 | L8: =J8*K8 -> 0 | M8: =L8-H8 -> 0 | N8: =H8-L8 -> 0
J9: =(H9+H9*0.2)/8 -> 0 | L9: =J9*K9 -> 0 | M9: =L9-H9 -> 0 | N9: =H9-L9 -> 0
J10: =(H10+H10*0.2)/8 -> 0 | L10: =J10*K10 -> 0 | M10: =L10-H10 -> 0 | N10: =H10-L10 -> 0
J11: =(H11+H11*0.2)/8 -> 0 | L11: =J11*K11 -> 0 | M11: =L11-H11 -> 0 | N11: =H11-L11 -> 0
J12: =(H12+H12*0.2)/8 -> 0 | L12: =J12*K12 -> 0 | M12: =L12-H12 -> 0 | N12: =H12-L12 -> 0

Sheet Expences & Other Income
A1: Date | B1: Other Income | D1: Date | E1: Expenses | O1: Total Ex
E2: Fuel | F2: Satam | G2: Card | H2: Photocopy | I2: Promisary | J2: Bick | K2: Other | L2: Rajith | N2: F | O2: =SUM(E:E) -> 4500
B3: rajakaru | E3: 1000 | F3: 1000 | G3: 900 | H3: 520 | I3: 400 | J3: 5500 | K3: 715 | L3: 1000 | N3: S | O3: =SUM(F:F) -> 5180
B4: leebdu | C4: 500 | E4: 1000 | F4: 360 | G4: 625 | H4: 200 | I4: 400 | J4: 4000 | K4: 1660 | L4: 500 | N4: C | O4: =SUM(G:G) -> 3525
E5: 500 | F5: 2220 | G5: 1250 | H5: 640 | I5: 480 | J5: 6320 | K5: 4580 | L5: 5000 | N5: P | O5: =SUM(H:H) -> 2185
E6: 2000 | F6: 1600 | G6: 750 | H6: 825 | I6: 1050 | J6: 3500 | K6: 4300 | L6: 5000 | N6: P | O6: =SUM(I:I) -> 2330

Sheet Profits
A1: Date | B1: Sumith | C1: Rajith | D1: Chamil | F1: Total Profit
B2: 62000 | C2: 62000 | D2: 62000 | E2: s | F2: =SUM(B:B) -> 62000

Sheet Bank Account
A1: No | B1: Date | H1: ATM | I1: Online
B2: 45901 | F2: 45901
B3: 45902 | F3: 45902
B4: 45903 | F4: 45903

Sheet cash 2025.09.04
A1: Date | B1: Sumith | C1: Chamil | D1: Rajith | E1: Cheqe In | F1: D/W in | H1: Month in | I1: Loan Settlement | J1: Interest in | K1: BOC | L1: Other | M1: Total Cash Received | N1: Cumulative | O1: Date | Q1: Description | R1: Daily | S1: Week | T1: Month Out 10% | U1: Month Out 5% | V1: BOC | W1: Fuel | X1: Sumith | Y1: Chamil | Z1: Rajith | AA1: Other | AB1: Total Out | AC1: Daily Cash Balance
A2: 45856 | B2: 200000 | C2: 0 | D2: 0 | M2: =+L2+B2+C2+D2+E2+F2+G2+H2 -> 200000 | N2: =M2 -> 200000 | O2: 45856 | R2: 65000 | T2: 50000 | AB2: =R2+T2+U2+V2+S2+W2+AA2 -> 115000 | AC2: =M2-AB2 -> 85000
A3: 45857 | B3: 150000 | C3: 40000 | D3: 0 | M3: =+L3+B3+C3+D3+E3+F3+G3+H3 -> 190000 | N3: =N2+M3 -> 390000 | O3: 45857 | R3: 50000 | AB3: =R3+T3+U3+V3+S3+W3+AA3 -> 50000 | AC3: =AC2+M3-AB3 -> 225000
A4: 45858 | B4: 0 | C4: 0 | D4: 0 | M4: =+L4+B4+C4+D4+E4+F4+G4+H4 -> 0 | N4: =N3+M4 -> 390000 | O4: 45858 | AB4: =R4+T4+U4+V4+S4+W4+AA4 -> 0 | AC4: =AC3+M4-AB4 -> 225000
A5: 45859 | B5: 0 | C5: 0 | D5: 0 | M5: =+L5+B5+C5+D5+E5+F5+G5+H5 -> 0 | N5: =N4+M5 -> 390000 | O5: 45859 | R5: 110000 | AB5: =R5+T5+U5+V5+S5+W5+AA5 -> 110000 | AC5: =AC4+M5-AB5 -> 115000
A6: 45860 | B6: 140000 | C6: 0 | D6: 0 | M6: =+L6+B6+C6+D6+E6+F6+G6+H6+I6 -> 140000 | N6: =N5+M6 -> 530000 | O6: 45860 | R6: 50000 | AB6: =R6+T6+U6+V6+S6+W6+AA6 -> 50000 | AC6: =AC5+M6-AB6 -> 205000
A7: 45861 | B7: 0 | C7: 0 | D7: 0 | M7: =+L7+B7+C7+D7+E7+F7+G7+H7+I7 -> 0 | N7: =N6+M7 -> 530000 | O7: 45861 | T7: 15000 | AB7: =R7+T7+U7+V7+S7+W7+AA7 -> 15000 | AC7: =AC6+M7-AB7 -> 190000
A8: 45862 | B8: 0 | C8: 0 | D8: 0 | M8: =+L8+B8+C8+D8+E8+F8+G8+H8+I8 -> 0 | N8: =N7+M8 -> 530000 | O8: 45862 | R8: 40000 | W8: 1000 | AB8: =R8+T8+U8+V8+S8+W8+AA8 -> 41000 | AC8: =AC7+M8-AB8 -> 149000
A9: 45863 | B9: 170000 | C9: 0 | D9: 0 | M9: =+L9+B9+C9+D9+E9+F9+G9+H9+I9 -> 170000 | N9: =N8+M9 -> 700000 | O9: 45863 | R9: 60000 | V9: 73000 | W9: 1000 | AB9: =R9+T9+U9+V9+S9+W9+AA9 -> 134000 | AC9: =AC8+M9-AB9 -> 185000
A10: 45864 | B10: 0 | C10: 0 | D10: 0 | M10: =+L10+B10+C10+D10+E10+F10+G10+H10+I10 -> 0 | N10: =N9+M10 -> 700000 | O10: 45864 | R10: 20000 | AB10: =R10+T10+U10+V10+S10+W10+AA10 -> 20000 | AC10: =AC9+M10-AB10 -> 165000
A11: 45865 | B11: 0 | C11: 0 | D11: 0 | M11: =+L11+B11+C11+D11+E11+F11+G11+H11+I11 -> 0 | N11: =N10+M11 -> 700000 | O11: 45865 | AB11: =R11+T11+U11+V11+S11+W11+AA11 -> 0 | AC11: =AC10+M11-AB11 -> 165000
A12: 45866 | B12: 0 | C12: 0 | D12: 0 | E12: 73000 | J12: 1250 | M12: =+L12+B12+C12+D12+E12+F12+G12+H12+I12+J12+K12 -> 74250 | N12: =N11+M12 -> 774250 | O12: 45866 | AB12: =R12+T12+U12+V12+S12+W12+AA12 -> 0 | AC12: =AC11+M12-AB12 -> 239250
A13: 45867 | B13: 0 | C13: 0 | D13: 0 | J13: 3000 | M13: =+L13+B13+C13+D13+E13+F13+G13+H13+I13+J13+K13 -> 3000 | N13: =N12+M13 -> 777250 | O13: 45867 | R13: 170000 | T13: 50000 | AB13: =R13+T13+U13+V13+S13+W13+AA13 -> 220000 | AC13: =AC12+M13-AB13 -> 22250
A14: 45868 | B14: 100000 | C14: 0 | D14: 0 | M14: =+L14+B14+C14+D14+E14+F14+G14+H14+I14+J14+K14 -> 100000 | N14: =N13+M14 -> 877250 | O14: 45868 | R14: 45000 | T14: 10000 | AB14: =R14+T14+U14+V14+S14+W14+AA14 -> 55000 | AC14: =AC13+M14-AB14 -> 67250
A15: 45869 | B15: 300000 | C15: 0 | D15: 0 | M15: =+L15+B15+C15+D15+E15+F15+G15+H15+I15+J15+K15 -> 300000 | N15: =N14+M15 -> 1177250 | O15: 45869 | T15: =20000+25000 -> 45000 | V15: 300000 | W15: 500 | AB15: =R15+T15+U15+V15+S15+W15+AA15 -> 345500 | AC15: =AC14+M15-AB15 -> 21750 | AD15: correct
AB16: =R16+T16+U16+V16+S16+W16+AA16 -> 0

Sheet Capital Edited
C1: Sumith | E1: Chamil | G1: Rajith
A2: Date | B2: Description | C2: IN | D2: Out | E2: In | F2: Out | G2: In | H2: Out | I2: CSR | J2: Total Investment | K2: Cumulative
A3: 45856 | C3: 200000 | E3: 0 | G3: 0 | I3: 0 | J3: =C3+E3+G3+I3 -> 200000 | K3: =J3 -> 200000
A4: 45857 | C4: 150000 | E4: 40000 | G4: 0 | I4: 0 | J4: =C4+E4+G4+I4 -> 190000 | K4: =K3+J4 -> 390000
A5: 45858 | C5: 52000 | D5: 52000 | E5: 0 | G5: 0 | I5: 0 | J5: =C5+E5+G5+I5 -> 52000 | K5: =K4+J5 -> 442000
A6: 45859 | C6: 0 | E6: 0 | G6: 0 | I6: 0 | J6: =C6+E6+G6+I6 -> 0 | K6: =K5+J6 -> 442000
A7: 45860 | C7: 140000 | E7: 0 | G7: 0 | I7: 0 | J7: =C7+E7+G7+I7 -> 140000 | K7: =K6+J7 -> 582000
A8: 45861 | C8: 0 | E8: 0 | G8: 0 | I8: 0 | J8: =C8+E8+G8+I8 -> 0 | K8: =K7+J8 -> 582000

Sheet Creditors
A1: Lahiru | E1: Tharindu | I1: Thimira
A2: Date | B2: in | C2: out | D2: Balance | E2: Date | F2: in | G2: out | H2: Balance | I2: Date | J2: in | K2: out | L2: Balance
D3: =B3-C3 -> 0 | H3: =F3-G3 -> 0 | L3: =J3 -> 0
D4: =B4-C4 -> 0 | H4: =F4-G4 -> 0 | L4: =L3+J4-K4 -> 0
D5: =B5-C5 -> 0 | H5: =F5-G5 -> 0 | L5: =L4+J5-K5 -> 0
D6: =B6-C6 -> 0 | H6: =F6-G6 -> 0 | L6: =L5+J6-K6 -> 0
D7: =B7-C7 -> 0 | H7: =F7-G7 -> 0 | L7: =L6+J7-K7 -> 0
D8: =B8-C8 -> 0 | H8: =F8-G8 -> 0 | L8: =L7+J8-K8 -> 0
D9: =B9-C9 -> 0 | H9: =F9-G9 -> 0 | I9: 45956 | J9: 100000 | L9: =L8+J9-K9 -> 100000
D10: =B10-C10 -> 0 | H10: =F10-G10 -> 0 | I10: 45959 | K10: 50000 | L10: =L9+J10-K10 -> 50000
A11: 45954 | C11: 50000 | D11: =B11-C11 -> -50000 | H11: =F11-G11 -> 0 | I11: 45960 | J11: 300000 | L11: =L10+J11-K11 -> 350000
D12: =B12-C12 -> 0 | H12: =F12-G12 -> 0 | I12: 45961 | K12: 50000 | L12: =L11+J12-K12 -> 300000
D13: =B13-C13 -> 0 | E13: 45960 | F13: 500000 | H13: =F13-G13 -> 500000 | L13: =L12+J13-K13 -> 300000
D14: =B14-C14 -> 0 | H14: =F14-G14 -> 0 | L14: =L13+J14-K14 -> 300000
D15: =B15-C15 -> 0 | H15: =F15-G15 -> 0 | L15: =L14+J15-K15 -> 300000
D16: =B16-C16 -> 0 | H16: =F16-G16 -> 0 | L16: =L15+J16-K16 -> 300000
D17: =B17-C17 -> 0 | H17: =F17-G17 -> 0 | L17: =L16+J17-K17 -> 300000

Sheet Debtors
B1: CID | C1: 1 | D1: 2 | E1: 3 | F1: 4 | G1: 5 | H1: 6 | I1: 7 | J1: 8 | K1: 9 | L1: 10 | M1: 11 | N1: 12 | O1: 13 | P1: 14 | Q1: 15 | R1: 16 | S1: 17 | T1: 18 | U1: 19 | V1: 20 | W1: 21 | X1: 22 | Y1: 23 | Z1: 24 | AA1: 25 | AB1: 26 | AC1: 27 | AD1: 28 | AE1: 29 | AF1: 30 | AG1: 31 | AH1: 32 | AI1: 33 | AJ1: 34 | AK1: 35 | AL1: 36 | AM1: 37 | AN1: 38 | AO1: 39 | AP1: 40 | AQ1: 41 | AR1: 42 | AS1: 43 | AT1: 44 | AU1: 45 | AV1: 46 | AW1: 47 | AX1: 48 | AY1: 49 | AZ1: 50 | BA1: 51 | BB1: 52 | BC1: 53 | BD1: 54 | BE1: 55 | BF1: 56 | BG1: 57 | BH1: 58 | BI1: 59 | BJ1: 60 | BK1: 61 | BL1: 62 | BM1: 63 | BN1: 64 | BO1: 65 | BP1: 66 | BQ1: 67 | BR1: 68 | BS1: 69 | BT1: 70 | BU1: 71
B2: Name | C2: BH Suragani | D2: BH Shiryani | E2: KBTD Chamani | F2: K A Prasanna | G2: H A Nandasena
B3: T.P | C3: 767850049 | D3: 783891636 | E3: 779907450 | F3: 776038166 | G3: 768675303
B4: Isuue date | C4: 45856 | D4: 45856 | E4: 45856 | F4: 45857 | G4: 45859 | H4: 45859 | I4: 45860 | J4: 45861 | K4: 45862 | L4: 45863 | M4: 45864 | N4: 45865 | O4: 45866 | P4: 45867 | Q4: 45868 | R4: 45869 | S4: 45870 | T4: 45871 | U4: 45872 | V4: 45873 | W4: 45874 | X4: 45875 | Y4: 45876 | Z4: 45877 | AA4: 45878 | AB4: 45879 | AC4: 45880 | AD4: 45881 | AE4: 45882 | AF4: 45883 | AG4: 45884 | AH4: 45885 | AI4: 45886 | AJ4: 45887 | AK4: 45888 | AL4: 45889 | AM4: 45890 | AN4: 45891 | AO4: 45892 | AP4: 45893 | AQ4: 45894 | AR4: 45895 | AS4: 45896 | AT4: 45897 | AU4: 45898 | AV4: 45899 | AW4: 45900 | AX4: 45901 | AY4: 45902 | AZ4: 45903 | BA4: 45904 | BB4: 45905 | BC4: 45906 | BD4: 45907 | BE4: 45908 | BF4: 45909 | BG4: 45910 | BH4: 45911 | BI4: 45912 | BJ4: 45913 | BK4: 45914 | BL4: 45915 | BM4: 45916 | BN4: 45917 | BO4: 45918 | BP4: 45919 | BQ4: 45920
B5: Installment | C5: 3000 | D5: 3000 | E5: 500 | F5: 1000 | G5: 1200
B6: No of instolment | C6: 8 | D6: 8 | E6: 60 | F6: 60 | G6: 60 | H6: 60
B7: Due date | C7: Weekly | D7: Weekly | E7: Daily | F7: Daily | G7: Daily | H7: Daily | I7: Daily | J7: Daily | K7: Daily | L7: Daily | M7: Daily
B8: Loan Amount | C8: 20000 | D8: 20000 | E8: 20000 | F8: 20000 | G8: 20000 | H8: 20000 | I8: 20000 | J8: 20000 | K8: 20000 | L8: 20000 | M8: 20000
B9: Total Payments | C9: =C5*C6 -> 24000 | D9: =D5*D6 -> 24000 | E9: =E5*E6 -> 30000 | F9: =F5*F6 -> 60000 | G9: =G5*G6 -> 72000 | H9: =H5*H6 -> 0 | I9: =I5*I6 -> 0 | J9: =J5*J6 -> 0 | ... M9: =M5*M6 -> 0
B10: Interest Rate | C10: 0.1 | D10: 0.1 | E10: 0.1 | F10: 0.1 | G10: 0.1 | H10: 0.1 | I10: 0.1 | J10: 0.1 | K10: 0.1 | L10: 0.1 | M10: 0.1 | N10: 0.1 | O10: 0.1 | P10: 0.1 | Q10: 0.1 | R10: 0.1 | S10: 0.1 | T10: 0.1 | U10: 0.1 | V10: 0.1 | W10: 0.1 | X10: 0.1 | Y10: 0.1 | Z10: 0.1 | AA10: 0.1 | AB10: 0.1 | AC10: 0.1 | AD10: 0.1 | AE10: 0.1 | AF10: 0.1 | AG10: 0.1 | AH10: 0.1 | AI10: 0.1 | AJ10: 0.1 | AK10: 0.1 | AL10: 0.1 | AM10: 0.1 | AN10: 0.1 | AO10: 0.1 | AP10: 0.1 | AQ10: 0.1 | AR10: 0.1 | AS10: 0.1 | AT10: 0.1 | AU10: 0.1 | AV10: 0.1 | AW10: 0.1 | AX10: 0.1 | AY10: 0.1 | AZ10: 0.1 | BA10: 0.1 | BB10: 0.1 | BC10: 0.1 | BD10: 0.1 | BE10: 0.1 | BF10: 0.1 | BG10: 0.1 | BH10: 0.1 | BI10: 0.1 | BJ10: 0.1 | BK10: 0.1 | BL10: 0.1 | BM10: 0.1
B11: Interest | C11: =C9-C8 -> 4000 | D11: =D9-D8 -> 4000 | E11: =E9-E8 -> 10000 | F11: =F9-F8 -> 40000 | G11: =G9-G8 -> 52000 | H11: =H9-H8 -> -20000 | I11: =I9-I8 -> -20000 | J11: =J9-J8 -> -20000 | ... GC11: =GC9-GC8 -> 0
B12: To be Received | C12: =C9-SUM(C13:C113) -> 18000
B13: 45857
C19: 3000
C26: 3000
